TwoCaptcha/__init__.py
TwoCaptcha/async_client.py
TwoCaptcha/client.py
TwoCaptcha/create_task.py
TwoCaptcha/exceptions.py
TwoCaptcha/get_balance.py
TwoCaptcha/get_task_result.py
TwoCaptcha/sync_client.py
twocaptcha_python-0.0.3.dist-info/METADATA
twocaptcha_python-0.0.3.dist-info/WHEEL
twocaptcha_python-0.0.3.dist-info/RECORD
