Metadata-Version: 2.4
Name: twocaptcha-python
Version: 0.0.3
Summary: Python client for 2captcha solving service - Bypass reCAPTCHA, Cloudflare Turnstile, FunCaptcha, GeeTest and solve any other captchas
Project-URL: Homepage, https://github.com/SSujitX/twocaptcha-python
Project-URL: Repository, https://github.com/SSujitX/twocaptcha-python
Project-URL: Documentation, https://github.com/SSujitX/twocaptcha-python#readme
Project-URL: Issues, https://github.com/SSujitX/twocaptcha-python/issues
Project-URL: Bug Tracker, https://github.com/SSujitX/twocaptcha-python/issues
Author-email: Sujit Biswas <ssujitxx@gmail.com>
Maintainer-email: Sujit Biswas <ssujitxx@gmail.com>
License: MIT
Keywords: 2captcha,2captcha api,2captcha api python,2captcha api python client,api,automation,captcha bypass,captcha solver,captcha solving service,client,cloudflare turnstile,funcaptcha,geetest,hcaptcha,image-captcha,python,recaptcha,recaptcha bypass,text-captcha,twocaptcha
Classifier: Development Status :: 4 - Beta
Classifier: Intended Audience :: Developers
Classifier: License :: OSI Approved :: MIT License
Classifier: Operating System :: OS Independent
Classifier: Programming Language :: Python :: 3
Classifier: Programming Language :: Python :: 3.9
Classifier: Programming Language :: Python :: 3.10
Classifier: Programming Language :: Python :: 3.11
Classifier: Programming Language :: Python :: 3.12
Classifier: Programming Language :: Python :: 3.13
Classifier: Topic :: Internet :: WWW/HTTP :: Dynamic Content
Classifier: Topic :: Software Development :: Libraries :: Python Modules
Classifier: Topic :: Software Development :: Testing
Classifier: Topic :: System :: Networking
Requires-Python: >=3.9
Requires-Dist: httpx>=0.28.1
Requires-Dist: rich>=14.2.0
